{ "_id" : { "$oid" : "4e7b89807a9d4e2cdd000003" }, "name" : "Complexity", "count" : 1, "_class" : "Models::Tag" }
{ "_id" : { "$oid" : "4e7b89807a9d4e2cdd000004" }, "name" : "DI", "count" : 1, "_class" : "Models::Tag" }
{ "_id" : { "$oid" : "4e7b89807a9d4e2cdd000005" }, "name" : "IoC", "count" : 1, "_class" : "Models::Tag" }
{ "_id" : { "$oid" : "4e7b89807a9d4e2cdd000006" }, "name" : "_class:Models::Note", "count" : 3, "context" : "_class", "_class" : "Models::Tag" }
{ "_id" : { "$oid" : "4e7b9f9b7a9d4e31fc000002" }, "name" : "Administration", "count" : 1, "_class" : "Models::Tag" }
{ "_id" : { "$oid" : "4e7b9f9b7a9d4e31fc000003" }, "name" : "S3", "count" : 1, "_class" : "Models::Tag" }
{ "_id" : { "$oid" : "4e7b9f9b7a9d4e31fc000004" }, "name" : "SSH", "count" : 1, "_class" : "Models::Tag" }
{ "_id" : { "$oid" : "4e7ba4dd7a9d4e31fc000009" }, "name" : "MongoDB", "count" : 1, "_class" : "Models::Tag" }
{ "_id" : { "$oid" : "4e7ba4dd7a9d4e31fc00000b" }, "name" : "Project", "count" : 3, "_class" : "Models::Tag" }
